master_agent/envs/__init__.py
master_agent/envs/complexEnv.py
master_agent/envs/grid_objects.py
master_agent/envs/keyOneEnv.py
master_agent/envs/keyTwoEnv.py
master_agent/envs/lavaIsWallEnv.py
master_agent/envs/noLavaEnv.py
master_agent/envs/noLavaKeyOneEnv.py
master_agent/envs/noLavaKeyTwoEnv.py
master_agent/envs/test_envs.py
master_agent/llm/__init__.py
master_agent/llm/client.py
master_agent/llm/identify.py
master_agent/llm/subtasks.py
master_agent/llm/test_client.py
master_agent/llm/test_identify.py
master_agent/llm/test_subtasks.py
master_agent/llm/utils.py
master_agent/llm/dataset/files/minigrid-actions.py
master_agent/llm/dataset/files/minigrid-constants.py
master_agent/llm/dataset/imgs/agent.png
master_agent/llm/dataset/imgs/box.png
master_agent/llm/dataset/imgs/door.png
master_agent/llm/dataset/imgs/empty.png
master_agent/llm/dataset/imgs/goal.png
master_agent/llm/dataset/imgs/key.png
master_agent/llm/dataset/imgs/lava.png
master_agent/llm/dataset/imgs/wall.png
master_agent/rl/__init__.py
master_agent/rl/consts.py
master_agent/rl/dag.py
master_agent/rl/feature_extractor.py
master_agent/rl/subtask.py
master_agent/rl/teacher_student.py
master_agent/rl/test_human_mode.py
master_agent/rl/test_reward.py
master_agent/rl/test_run.py
master_agent/rl/test_subtask.py
master_agent/rl/utils/__init__.py
master_agent/rl/utils/common.py
master_agent/rl/utils/string_parser.py
master_agent-0.0.695.dist-info/licenses/LICENCE
master_agent-0.0.695.dist-info/METADATA
master_agent-0.0.695.dist-info/WHEEL
master_agent-0.0.695.dist-info/top_level.txt
master_agent-0.0.695.dist-info/RECORD
