Metadata-Version: 2.4
Name: master_agent
Version: 0.0.695
Summary: A library providing the tools to solve complex environments in Minigrid using LgTS
Author: Stevo Huncho
Author-email: stevo@stevohuncho.com
Keywords: reinforcement learning,actor-critic,a2c,ppo,multi-processes,gpu,teacher student,ts
License-File: LICENCE
Requires-Dist: torch
Requires-Dist: minigrid
Requires-Dist: numpy
Requires-Dist: gymnasium
Requires-Dist: stable_baselines3
Requires-Dist: opencv-python
Requires-Dist: imageio
Requires-Dist: matplotlib
Requires-Dist: openai
Dynamic: author
Dynamic: author-email
Dynamic: description
Dynamic: description-content-type
Dynamic: keywords
Dynamic: license-file
Dynamic: requires-dist
Dynamic: summary
